ezmcp-0.0.2.dist-info/METADATA
ezmcp-0.0.2.dist-info/WHEEL
ezmcp-0.0.2.dist-info/entry_points.txt
ezmcp/README.md
ezmcp/__init__.py
ezmcp/app.py
ezmcp/middleware.py
ezmcp/templates.py
ezmcp/types.py
ezmcp-0.0.2.dist-info/RECORD
