Metadata-Version: 2.1
Name: ezmcp
Version: 0.0.2
Summary: Easy-to-use MCP server framework specialized for SSE.
Author-Email: jujumilk3 <jujumilk3@gmail.com>
License: MIT
Classifier: Typing :: Typed
Classifier: Topic :: Software Development :: Libraries :: Python Modules
Classifier: License :: OSI Approved :: MIT License
Classifier: Programming Language :: Python
Classifier: Programming Language :: Python :: 3
Classifier: Programming Language :: Python :: 3 :: Only
Classifier: Programming Language :: Python :: 3.10
Classifier: Programming Language :: Python :: 3.11
Classifier: Programming Language :: Python :: 3.12
Classifier: Programming Language :: Python :: 3.13
Project-URL: homepage, https://github.com/jujumilk3/ezmcp
Project-URL: bug-tracker, https://github.com/jujumilk3/ezmcp/issues
Requires-Python: >=3.10
Requires-Dist: mcp<=2.0.0,>=1.3.0
Provides-Extra: test
Requires-Dist: pytest; extra == "test"
Provides-Extra: dev
Requires-Dist: pytest; extra == "dev"
Requires-Dist: ruff; extra == "dev"
